{"message": "hi", "status": "done", "feedback": " Hello! It's a pleasure to meet you. As the CEO of our AI development organization, I oversee the strategic direction, workflow coordination, resource allocation, and quality assurance oversight. I have two primary teams under me - Workers and QA. The Worker team is responsible for code implementation, task execution, and technical problem solving. Our Quality Assurance team conducts code review, quality checks, and testing to ensure our output meets the highest standards. If you have any requests or tasks, please let me know, and I will analyze it, plan an approach, decide on the next step, and explain my reasoning before assigning it to the appropriate team.", "thought_process": "ANALYZE: Processing request about hi\nPLAN: Providing comprehensive response as CEO\nDECIDE: END\nEXPLAIN: Completed direct response to user inquiry", "session_id": "1749545075736"}